recallbricks/__init__.py
recallbricks/client.py
recallbricks/exceptions.py
recallbricks/types.py
recallbricks-1.5.1.dist-info/METADATA
recallbricks-1.5.1.dist-info/WHEEL
recallbricks-1.5.1.dist-info/top_level.txt
recallbricks-1.5.1.dist-info/RECORD
